solarkat/__init__.py
solarkat/solarkat-cabs.yaml
solarkat/solarkat-observation-sets.yaml
solarkat/solarkat.py
solarkat/solarkat.yaml
solarkat-1.0.6.dist-info/LICENSE
solarkat-1.0.6.dist-info/METADATA
solarkat-1.0.6.dist-info/WHEEL
solarkat-1.0.6.dist-info/RECORD
