Metadata-Version: 2.3
Name: solarkat
Version: 1.0.6
Summary: Solar imaging pipeline for solar interference mitigation in MeerKAT data.
License: MIT
Author: Victória da Graça G. Samboco
Author-email: vicky.samboco@gmail.com
Requires-Python: >=3.9,<4.0
Classifier: Development Status :: 4 - Beta
Classifier: Intended Audience :: Science/Research
Classifier: License :: OSI Approved :: MIT License
Classifier: Operating System :: POSIX :: Linux
Classifier: Programming Language :: Python :: 3
Classifier: Programming Language :: Python :: 3.9
Classifier: Programming Language :: Python :: 3.10
Classifier: Programming Language :: Python :: 3.11
Classifier: Programming Language :: Python :: 3.12
Classifier: Programming Language :: Python :: 3.13
Classifier: Topic :: Scientific/Engineering :: Astronomy
Requires-Dist: cult-cargo (>=0.2.0,<0.3.0)
Requires-Dist: stimela (>=2.0.1,<3.0.0)
Project-URL: Documentation, https://solarkat-docs.readthedocs.io/en/latest/
Project-URL: Repository, https://github.com/ratt-ru/solarkat.git
